bcda_client/__init__.py
bcda_client/client.py
bcda_client/config.py
bcda_client/utils.py
bcda_client_datant-0.2.0.dist-info/LICENSE
bcda_client_datant-0.2.0.dist-info/METADATA
bcda_client_datant-0.2.0.dist-info/WHEEL
bcda_client_datant-0.2.0.dist-info/top_level.txt
bcda_client_datant-0.2.0.dist-info/RECORD
