Metadata-Version: 2.2
Name: bcda-client-datant
Version: 0.2.0
Summary: A Python client for the BCDA (Beneficiary Claims Data API)
Home-page: https://github.com/pachecocarlos27/bcda-client
Author: Carlos Pacheco
Author-email: admin@data-nt.com
Project-URL: Bug Tracker, https://github.com/pachecocarlos27/bcda-client/issues
Project-URL: Documentation, https://github.com/pachecocarlos27/bcda-client#readme
Keywords: healthcare,bcda,cms,medicare,api-client
Classifier: Development Status :: 3 - Alpha
Classifier: Intended Audience :: Science/Research
Classifier: Intended Audience :: Developers
Classifier: Programming Language :: Python :: 3
Classifier: Programming Language :: Python :: 3.6
Classifier: Programming Language :: Python :: 3.7
Classifier: Programming Language :: Python :: 3.8
Classifier: Programming Language :: Python :: 3.9
Classifier: License :: OSI Approved :: MIT License
Classifier: Operating System :: OS Independent
Classifier: Topic :: Software Development :: Libraries :: Python Modules
Classifier: Topic :: Scientific/Engineering :: Medical Science Apps.
Requires-Python: >=3.6
License-File: LICENSE
Requires-Dist: requests>=2.25.0
Requires-Dist: pandas>=1.0.0
Requires-Dist: pyarrow>=3.0.0
Requires-Dist: tqdm
Requires-Dist: pytest>=6.0.0
Requires-Dist: pytest-benchmark>=3.4.1
Requires-Dist: psutil>=5.8.0
Requires-Dist: pyarrow>=3.0.0
Requires-Dist: pandas>=1.0.0
Dynamic: author
Dynamic: author-email
Dynamic: classifier
Dynamic: description
Dynamic: description-content-type
Dynamic: home-page
Dynamic: keywords
Dynamic: project-url
Dynamic: requires-dist
Dynamic: requires-python
Dynamic: summary
